sonar/__init__.py
sonar/cli.py
sonar/map.py
sonar/probe.py
sonar/version.py
sonar/mapping/regex_map.txt
sonar/mapping/string_map.txt
sonar-0.5.0.dist-info/entry_points.txt
sonar-0.5.0.dist-info/LICENSE
sonar-0.5.0.dist-info/WHEEL
sonar-0.5.0.dist-info/METADATA
sonar-0.5.0.dist-info/RECORD
