Metadata-Version: 2.1
Name: sonar
Version: 0.5.0
Summary: Sonar: Tool to profile usage of HPC resources by regularly probing processes
Home-page: https://github.com/NordicHPC/sonar
Author: Radovan Bast
Author-email: radovan.bast@uit.no
Classifier: License :: OSI Approved :: GNU General Public License v3 (GPLv3)
Requires-Dist: tqdm
